mlx/__init__.py
mlx/sdk/__init__.py
mlx/sdk/data/__init__.py
ncloud_mlx_data_manager-0.1.0.dist-info/METADATA
ncloud_mlx_data_manager-0.1.0.dist-info/WHEEL
ncloud_mlx_data_manager-0.1.0.dist-info/licenses/LICENSE
ncloud_mlx_data_manager-0.1.0.dist-info/RECORD
