Metadata-Version: 2.4
Name: ncloud-mlx-data-manager
Version: 0.1.0
Summary: ML expert Platform Data Manager SDK - Hugging Face compatible dataset management library
Project-URL: Homepage, https://guide.ncloud-docs.com/docs/ai-mlxp-datamanager
Project-URL: Documentation, https://guide.ncloud-docs.com/docs/ai-mlxp-datamanager
Author-email: navercloud-mlxp <dl_mlx_ncp_dev@navercorp.com>
License-Expression: Apache-2.0
License-File: LICENSE
Requires-Python: <4.0.0,>=3.9.0
Requires-Dist: boto3~=1.34.95
Requires-Dist: clear-cache==1.0.0
Requires-Dist: datasets==3.2.0
Requires-Dist: fsspec==2023.5.0
Requires-Dist: huggingface-hub==0.28.0
Requires-Dist: librosa==0.10.2.post1
Requires-Dist: pandas~=2.2.0
Requires-Dist: pillow~=11.2.1
Requires-Dist: pyarrow<21.0.0,>=20.0.0
Requires-Dist: rich>=13.4.2
Requires-Dist: soundfile==0.12.1
Requires-Dist: zstandard==0.23.0
